cpu project/parts_made/div.v
module div (
    input wire [31:0] srcA, // numerator 
    input wire [31:0] srcB, // denominator
    input wire clk,
    input wire reset,
    input wire divCtrl, // DivInit 
    output reg divZero,
    output reg [31:0] hi,
    output reg [31:0] lo
);

/*
- DivInit = 1 -> Load srcs and set divRun=1
- DivInit = 0 -> Do 1 operation; 32 cycles to finish 
    -- On cycle 32 set divRun=0
*Steps:
    1. quotient and remainder starts with zero; currDigit (of numerator) starts with 31
    2. shift remainder left and fill with the currDigit, then compare it with denominator
    3.  if denominator>remainder: shift left with 0 as the new LSB of the quotient 
        else: subtract to get new remainder and shift left with 1 as the new LSB of the quotient
    4.  if currDigit>0: do currDigit-=1 then goto 2.
        else: divRun = 0
*/	
    reg divRun, signalA, signalB, signalQuot;
    reg [31:0] numerator, quotient; // intermediates for srcA and lo
    reg [31:0] denominator, remainder; // intermediates for srcB and hi
    reg [5:0] cycleCount, currDigit;

    always @ (posedge clk) begin
		if (reset) begin
			numerator=32'b0; denominator=32'b0;
			quotient=32'b0; remainder=32'b0;

			currDigit=5'd31; cycleCount=5'd0;
            hi=32'b0; lo=32'b0;

			divRun = 0; divZero = 1;
		end
        else if(divCtrl) begin
            divZero = 1;
            if(srcB == 32'b0) begin
                divZero = 0;
            end 
            else begin
                signalA = srcA[31];
                signalB = srcB[31];
                signalQuot = signalA ^ signalB; 
                numerator = signalA ? ~srcA + 1 : srcA;
                denominator = signalB ? ~srcB + 1 : srcB;  

                quotient = 31'b0; remainder = 31'b0;
                divRun = 1'b1; divZero = 1'b1;
                currDigit = 5'd31; cycleCount = 5'd0;

                hi=32'b0; lo=32'b0;
                
                remainder = {remainder[29:0],numerator[currDigit]};
                if(denominator>remainder) begin
                    quotient = {quotient[29:0], 1'b0};
                end
                else begin
                    remainder = remainder - denominator;
                    quotient = {quotient[29:0],1'b1};  
                end
                cycleCount <= cycleCount+1'b1;
                currDigit = currDigit-1'b1;
            end
        end
        
        if(!divCtrl & divRun) begin 
            remainder = {remainder[29:0],numerator[currDigit]};
            if(denominator>remainder) begin
                quotient = {quotient[29:0], 1'b0};
            end
            else begin
                remainder = remainder - denominator;
                quotient = {quotient[29:0],1'b1};  
            end
            cycleCount <= cycleCount+1'b1;
            if(cycleCount==5'b11111) begin  // stop div
                divRun=0;
                hi = signalA ? ~remainder + 1 : remainder;
                lo = signalQuot ? ~quotient + 1 : quotient;
            end
            else begin //-1
                currDigit = currDigit-1'b1;
            end
        end
    end
endmodule

cpu project/parts_made/test/div.v
`timescale 1ns / 1ps

`include "div.v"

module divider_tb;
   parameter n_bits = 32;
	
	// Inputs
	reg [n_bits-1:0] a_in;
	reg [n_bits-1:0] b_in;
	reg clk;
	reg start;
	reg reset;
    wire divZero;

	// Outputs
	wire [n_bits-1:0] hi;
	wire [n_bits-1:0] lo;

	// Instantiate the Unit Under Test (UUT)
	div uut (
		.srcA(a_in), 
		.srcB(b_in), 
		.clk(clk), 
		.divCtrl(start), 
		.reset(reset),
        .divZero(divZero), 
		.hi(hi), 
		.lo(lo)
	);

	initial
	begin
	forever 
		#50 clk= ~clk;
	end
	
	initial begin
        $dumpfile("test.vcd");
        $dumpvars(1, uut);
		// Initialize Inputs
		a_in = 0;
		b_in = 0;
		clk = 0;
		start = 0;
		reset = 1;

		// Wait 100 ns for global reset to finish
		#100;
        
		// Add stimulus here
		reset = 0;
        #100
        a_in = ~'d25+1;
		b_in = 'd6;
		start = 1;
		#100
		start = 0;
		#(100*n_bits)
        $display("hi = %b, lo = %b, a_in = %b, b_in = %b", hi, lo, a_in, b_in);
        #200
		a_in = 'd190 ;
		b_in = 'd13 ;
		start = 1;
		#100
		start = 0;
		#(100*n_bits)
        $display("hi = %d, lo = %d", hi, lo);
		$finish;
	end
      
endmodule

cpu project/parts_made/test.vcd
$date
	Sun Jun 23 19:58:44 2024
$end
$version
	Icarus Verilog
$end
$timescale
	1ps
$end
$scope module divider_tb $end
$scope module uut $end
$var wire 1 ! clk $end
$var wire 1 " divCtrl $end
$var wire 1 # reset $end
$var wire 32 $ srcA [31:0] $end
$var wire 32 % srcB [31:0] $end
$var reg 6 & currDigit [5:0] $end
$var reg 6 ' cycleCount [5:0] $end
$var reg 32 ( denominator [31:0] $end
$var reg 1 ) divRun $end
$var reg 1 * divZero $end
$var reg 32 + hi [31:0] $end
$var reg 32 , lo [31:0] $end
$var reg 32 - numerator [31:0] $end
$var reg 32 . quotient [31:0] $end
$var reg 32 / remainder [31:0] $end
$var reg 1 0 signalA $end
$var reg 1 1 signalB $end
$var reg 1 2 signalQuot $end
$upscope $end
$upscope $end
$enddefinitions $end
$comment Show the parameter values. $end
$dumpall
$end
#0
$dumpvars
x2
x1
x0
bx /
bx .
bx -
bx ,
bx +
x*
x)
bx (
bx '
bx &
b0 %
b0 $
1#
0"
0!
$end
#50000
1*
0)
b0 ,
b0 +
b0 '
b11111 &
b0 /
b0 .
b0 (
b0 -
1!
#100000
0!
0#
#150000
1!
#200000
0!
1"
b110 %
b11111111111111111111111111100111 $
#250000
1)
b110 (
b11001 -
12
01
10
1!
#300000
0!
0"
#350000
b1 '
b11110 &
1!
#400000
0!
#450000
b10 '
b11101 &
1!
#500000
0!
#550000
b11 '
b11100 &
1!
#600000
0!
#650000
b100 '
b11011 &
1!
#700000
0!
#750000
b101 '
b11010 &
1!
#800000
0!
#850000
b110 '
b11001 &
1!
#900000
0!
#950000
b111 '
b11000 &
1!
#1000000
0!
#1050000
b1000 '
b10111 &
1!
#1100000
0!
#1150000
b1001 '
b10110 &
1!
#1200000
0!
#1250000
b1010 '
b10101 &
1!
#1300000
0!
#1350000
b1011 '
b10100 &
1!
#1400000
0!
#1450000
b1100 '
b10011 &
1!
#1500000
0!
#1550000
b1101 '
b10010 &
1!
#1600000
0!
#1650000
b1110 '
b10001 &
1!
#1700000
0!
#1750000
b1111 '
b10000 &
1!
#1800000
0!
#1850000
b10000 '
b1111 &
1!
#1900000
0!
#1950000
b10001 '
b1110 &
1!
#2000000
0!
#2050000
b10010 '
b1101 &
1!
#2100000
0!
#2150000
b10011 '
b1100 &
1!
#2200000
0!
#2250000
b10100 '
b1011 &
1!
#2300000
0!
#2350000
b10101 '
b1010 &
1!
#2400000
0!
#2450000
b10110 '
b1001 &
1!
#2500000
0!
#2550000
b10111 '
b1000 &
1!
#2600000
0!
#2650000
b11000 '
b111 &
1!
#2700000
0!
#2750000
b11001 '
b110 &
1!
#2800000
0!
#2850000
b11010 '
b101 &
1!
#2900000
0!
#2950000
b11011 '
b100 &
1!
#3000000
0!
#3050000
b11100 '
b11 &
b1 /
1!
#3100000
0!
#3150000
b11101 '
b10 &
b11 /
1!
#3200000
0!
#3250000
b11110 '
b1 &
b1 .
b0 /
1!
#3300000
0!
#3350000
b11111 '
b0 &
b10 .
1!
#3400000
0!
#3450000
b100000 '
b11111111111111111111111111111011 ,
b101 +
0)
b100 .
b1 /
1!
#3500000
0!
#3550000
1!
#3600000
0!
#3650000
1!
#3700000
0!
1"
b1101 %
b10111110 $
#3750000
b0 ,
b0 +
b0 '
b11111 &
1)
b0 /
b0 .
b1101 (
b10111110 -
02
00
1!
#3800000
0!
0"
#3850000
b1 '
b11110 &
1!
#3900000
0!
#3950000
b10 '
b11101 &
1!
#4000000
0!
#4050000
b11 '
b11100 &
1!
#4100000
0!
#4150000
b100 '
b11011 &
1!
#4200000
0!
#4250000
b101 '
b11010 &
1!
#4300000
0!
#4350000
b110 '
b11001 &
1!
#4400000
0!
#4450000
b111 '
b11000 &
1!
#4500000
0!
#4550000
b1000 '
b10111 &
1!
#4600000
0!
#4650000
b1001 '
b10110 &
1!
#4700000
0!
#4750000
b1010 '
b10101 &
1!
#4800000
0!
#4850000
b1011 '
b10100 &
1!
#4900000
0!
#4950000
b1100 '
b10011 &
1!
#5000000
0!
#5050000
b1101 '
b10010 &
1!
#5100000
0!
#5150000
b1110 '
b10001 &
1!
#5200000
0!
#5250000
b1111 '
b10000 &
1!
#5300000
0!
#5350000
b10000 '
b1111 &
1!
#5400000
0!
#5450000
b10001 '
b1110 &
1!
#5500000
0!
#5550000
b10010 '
b1101 &
1!
#5600000
0!
#5650000
b10011 '
b1100 &
1!
#5700000
0!
#5750000
b10100 '
b1011 &
1!
#5800000
0!
#5850000
b10101 '
b1010 &
1!
#5900000
0!
#5950000
b10110 '
b1001 &
1!
#6000000
0!
#6050000
b10111 '
b1000 &
1!
#6100000
0!
#6150000
b11000 '
b111 &
1!
#6200000
0!
#6250000
b11001 '
b110 &
b1 /
1!
#6300000
0!
#6350000
b11010 '
b101 &
b10 /
1!
#6400000
0!
#6450000
b11011 '
b100 &
b101 /
1!
#6500000
0!
#6550000
b11100 '
b11 &
b1011 /
1!
#6600000
0!
#6650000
b11101 '
b10 &
b1 .
b1010 /
1!
#6700000
0!
#6750000
b11110 '
b1 &
b11 .
b1000 /
1!
#6800000
0!
#6850000
b11111 '
b0 &
b111 .
b100 /
1!
#6900000
0!
#6950000
b100000 '
b1110 ,
b1000 +
0)
b1110 .
b1000 /
1!
